sqliteplus/__init__.py
sqliteplus/cli.py
sqliteplus/main.py
sqliteplus/_compat/__init__.py
sqliteplus/_compat/bcrypt.py
sqliteplus/_compat/bootstrap.py
sqliteplus/api/__init__.py
sqliteplus/api/endpoints.py
sqliteplus/auth/__init__.py
sqliteplus/auth/jwt.py
sqliteplus/auth/users.py
sqliteplus/core/__init__.py
sqliteplus/core/_schemas_columns.pxd
sqliteplus/core/_schemas_columns.pyx
sqliteplus/core/_schemas_constants.pxd
sqliteplus/core/_schemas_constants.py
sqliteplus/core/_schemas_fast.pxd
sqliteplus/core/_schemas_fast.pyx
sqliteplus/core/_schemas_py_fallback.py
sqliteplus/core/db.py
sqliteplus/core/logger.py
sqliteplus/core/schemas.py
sqliteplus/core/schemas.pyx
sqliteplus/utils/__init__.py
sqliteplus/utils/_replication_sync_py.py
sqliteplus/utils/constants.py
sqliteplus/utils/database_manager_sync.py
sqliteplus/utils/json_serialization.py
sqliteplus/utils/profiling.py
sqliteplus/utils/replication_sync.pxd
sqliteplus/utils/replication_sync.py
sqliteplus/utils/replication_sync.pyx
sqliteplus/utils/rich_compat.py
sqliteplus/utils/sqliteplus_sync.pxd
sqliteplus/utils/sqliteplus_sync.py
sqliteplus/utils/sqliteplus_sync.pyx
sqliteplus_enhanced-1.0.11.dist-info/licenses/LICENSE.md
sqliteplus_enhanced-1.0.11.dist-info/METADATA
sqliteplus_enhanced-1.0.11.dist-info/WHEEL
sqliteplus_enhanced-1.0.11.dist-info/entry_points.txt
sqliteplus_enhanced-1.0.11.dist-info/top_level.txt
sqliteplus_enhanced-1.0.11.dist-info/RECORD
