Metadata-Version: 2.4
Name: sqliteplus-enhanced
Version: 1.0.11
Summary: SQLite mejorado con cifrado SQLCipher y API REST asincrónica con FastAPI
Author-email: Adolfo González Hernández <adolfogonzal@gmail.com>
License-Expression: MIT
Classifier: Programming Language :: Python :: 3
Classifier: Programming Language :: Python :: 3.10
Classifier: Programming Language :: Python :: 3.11
Classifier: Framework :: FastAPI
Classifier: Operating System :: OS Independent
Classifier: Development Status :: 5 - Production/Stable
Requires-Python: >=3.10
License-File: LICENSE.md
Requires-Dist: aiosqlite
Requires-Dist: click
Requires-Dist: fastapi
Requires-Dist: uvicorn
Requires-Dist: PyJWT
Requires-Dist: python-multipart
Requires-Dist: rich
Provides-Extra: dev
Requires-Dist: httpx; extra == "dev"
Requires-Dist: pytest; extra == "dev"
Requires-Dist: pytest-asyncio; extra == "dev"
Requires-Dist: ruff; extra == "dev"
Provides-Extra: redis
Requires-Dist: redis; extra == "redis"
Provides-Extra: visual
Requires-Dist: fletplus; extra == "visual"
Requires-Dist: flet; extra == "visual"
Provides-Extra: security
Requires-Dist: bcrypt; extra == "security"
Provides-Extra: speedups
Requires-Dist: Cython>=3.0.0; extra == "speedups"
Dynamic: license-file
